LICENSE
MANIFEST.in
README.py
README.rst
gen_manifest.sh
setup.py
startup.py
examples/mul.py
startup.egg-info/PKG-INFO
startup.egg-info/SOURCES.txt
startup.egg-info/dependency_links.txt
startup.egg-info/top_level.txt
tests/__init__.py
tests/test_closure.py
tests/test_parse.py
tests/test_startup.py
tests/test_variable.py