Metadata-Version: 1.1
Name: startup
Version: 0.3.0
Summary: A dependency graph resolver for program startup
Home-page: https://github.com/clchiou/startup
Author: Che-Liang Chiou
Author-email: clchiou@gmail.com
License: MIT
Platform: *
Classifier: Development Status :: 1 - Planning
Classifier: Intended Audience :: Developers
Classifier: License :: OSI Approved :: MIT License
Classifier: Operating System :: OS Independent
Classifier: Programming Language :: Python :: 3 :: Only
Classifier: Topic :: Software Development :: Libraries :: Python Modules
